mcp_server.py
sdominanta_mcp-0.1.8.dist-info/METADATA
sdominanta_mcp-0.1.8.dist-info/WHEEL
sdominanta_mcp-0.1.8.dist-info/entry_points.txt
sdominanta_mcp-0.1.8.dist-info/top_level.txt
sdominanta_mcp-0.1.8.dist-info/RECORD
