Metadata-Version: 2.4
Name: sdominanta-mcp
Version: 0.1.8
Summary: Autonomous MCP server for Sdominanta.net (seed/schema/validators/wall signatures)
Author-email: "Sdominanta.net" <noreply@sdominanta.net>
Requires-Python: >=3.10
Requires-Dist: mcp[cli]>=1.2.0
Requires-Dist: jsonschema>=4.19.0
Requires-Dist: PyNaCl>=1.5.0
Requires-Dist: rfc8785>=0.1.1
